{
  "AttachmentsContent": [
    {
      "Hash": "001496dc1ad776830f9400a6024f6e7b0ed4f08522fb68bd03085e95f81e61ff",
      "HashType": {
        "Value": "Sha256"
      },
      "Name": "AwsEnaNetworkDriver-2.2.4.zip",
      "Size": 291715,
      "Url": "https://aws-ssm-document-attachments-us-west-2.s3.us-west-2.amazonaws.com/762/316874961013/AwsEnaNetworkDriver%210c9db6a3-ee9e-4591-bfde-7780a7770321/11/AwsEnaNetworkDriver-2.2.4.zip?x-attachment-size=291715&x-requester-accountId=987868780346&X-Amz-Security-Token=IQoJb3JpZ2luX2VjEIb%2F%2F%2F%2F%2F%2F%2F%2F%2F%2FwEaCXVzLXdlc3QtMiJIMEYCIQD1sznRn3mxhAjZdcgt%2Bfe84forxcgzpEpHhsrqkQ2U%2BwIhAJXy8G1Jsc8lQkIhw6zGhPQck%2BTcOFRiA9FM28w%2BxGhCKoMECM%2F%2F%2F%2F%2F%2F%2F%2F%2F%2F%2FwEQAxoMMjQ5OTI0NTI3NDEwIgz%2FLm04fhpIowhUyXUq1wPFMFuC%2BvllGUwm%2BFwqxzwqnWNukni90PC5VTOMiFNIPCzTj%2FwXsqQEKAPlFhOwo81%2FPUk7WEa1c%2FTPK6CFueofFyX81siPWeOC65x%2FxIPKPFFARPcSiiW3zuBsURfb949J4IhyWXCUZF8xbc2KtQXwrwS8fPo3b%2BXsbZIELg5voGFqMNjGy9tjzuGWYndssJChUqnMnnE4GiCNtdOq5GpTazoBXed1jK4bYt9IF8GDu%2Fl0G3HsqJAGAT2ezzaR57jriRpzhqy19f9x145qVkF%2F6g%2FlgfW1IZpRYe2S6DURLFsV3VMQephpd8Vtw8NtUP9YMMKZvb2sPi9LfxDlWLhOg%2Bdzk0Wlb57eXVV0S8dPQQQC46x0tVt%2Fuc%2BecLbK9RVQniVDS0GISfKMpjp7Z6%2FAIUWw8FLHwRRL8BzzNdRi8ZxT1%2Fb9Jceed%2BKLP10bY6d%2Fb4bVbYjA11F8P0N5AJk3e92GM4%2FMrtxXO3%2F%2FuTcitMH3CAV3HAniThKsznn0%2F2q0fE0HqKBWKDF1UKuNYjlz%2FuBvPLV7kmEchfeGH8SNLqVhz7fyzYSc9j03noARX1FOf0I0%2F2LjiY9tXbTzmAVDOUom83sGPQVsQi8igwWjwm%2BtKAAZSQAwrMa3kAY6pAGJKDvReRkAMgHw1T34TXasEkmUN1WX9vnNytICLxj4vCus49EHAmIPeioU%2Byg1gzrfMlH8MS5ikKbHqlb2XYh1a%2Boi4elx9HeqQAwwApKs0FQZAtHGu11joa46R0VQJ6GC8%2Bf%2B95wf1OnuFAD1qUmpvsJaTM%2FQVWBbsdabT2FMOLV31ZZhv41q7dwjC8dAlW0X9hTz65qpxUNq21TvB%2Bj2iz7feQ%3D%3D&X-Amz-Algorithm=AWS4-HMAC-SHA256&X-Amz-Date=20220217T071221Z&X-Amz-SignedHeaders=host&X-Amz-Expires=300&X-Amz-Credential=ASIATUMFJUUZLVDG5Y4U%2F20220217%2Fus-west-2%2Fs3%2Faws4_request&X-Amz-Signature=1a0cdf0d2147852fb881735d73e3f2656f75dfcd8925fd0f6633aaf0fd9af882"
    }
  ],
  "Content": "{\n    \"schemaVersion\": \"2.0\",\n    \"name\": \"AwsEnaNetworkDriver\",\n    \"version\": \"2.2.4\",\n    \"packageArn\": \"arn:aws:ssm:::package/AwsEnaNetworkDriver\",\n    \"publisher\": \"Amazon AWS\",\n    \"url\": \"https://amazonaws.com\",\n    \"packages\": {\n        \"windows\": {\n            \"_any\": {\n                \"x86_64\": {\n                    \"file\": \"AwsEnaNetworkDriver-2.2.4.zip\"\n                }\n            }\n        }\n    },\n    \"files\": {\n        \"AwsEnaNetworkDriver-2.2.4.zip\": {\n            \"checksums\": {\n                \"sha256\": \"001496DC1AD776830F9400A6024F6E7B0ED4F08522FB68BD03085E95F81E61FF\"\n            },\n            \"downloadLocation\": \"https://us-west-2-birdwatcher-prod.s3.us-west-2.amazonaws.com/316874961013/AwsEnaNetworkDriver-2.2.4.zip\"\n        }\n    }\n}",
  "CreatedDate": "2021-11-02T07:56:28.898Z",
  "DisplayName": null,
  "DocumentFormat": {
    "Value": "JSON"
  },
  "DocumentType": {
    "Value": "Package"
  },
  "DocumentVersion": "11",
  "Name": "AwsEnaNetworkDriver",
  "Requires": [],
  "ReviewStatus": null,
  "Status": {
    "Value": "Active"
  },
  "StatusInformation": null,
  "VersionName": "2.2.4",
  "ResponseMetadata": {
    "RequestId": "d93f5200-a25e-4f48-94ad-b2cab2fb0fb8",
    "Metadata": {}
  },
  "ContentLength": 2921,
  "HttpStatusCode": 200,
  "LoggedAt": "2022-02-17T07:12:21.6686207+00:00"
}
