{
  "AttachmentsContent": [],
  "Content": "{\n  \"description\" : \"sudo yum update\",\n  \"schemaVersion\" : \"2.2\",\n  \"parameters\" : {\n    \"package\" : {\n      \"type\" : \"String\",\n      \"description\" : \"package to be updated\",\n      \"default\" : \"kernel\"\n    }\n  },\n  \"mainSteps\" : [ {\n    \"action\" : \"aws:runShellScript\",\n    \"name\" : \"ConfigureKernelLivePatching\",\n    \"precondition\" : {\n      \"StringEquals\" : [ \"platformType\", \"Linux\" ]\n    },\n    \"inputs\" : {\n      \"timeoutSeconds\" : 7200,\n      \"runCommand\" : [ \"#!/bin/bash\", \"#\", \"yes | sudo yum update {{package}}\" ]\n    }\n  } ]\n}",
  "CreatedDate": "2023-02-03T15:46:01.84Z",
  "DisplayName": null,
  "DocumentFormat": {
    "Value": "JSON"
  },
  "DocumentType": {
    "Value": "Command"
  },
  "DocumentVersion": "1",
  "Name": "arn:aws:ssm:us-west-2:969837250943:document/sudo_yum_update",
  "Requires": [],
  "ReviewStatus": null,
  "Status": {
    "Value": "Active"
  },
  "StatusInformation": null,
  "VersionName": null,
  "ResponseMetadata": {
    "RequestId": "7d1807f2-7f6e-4f73-8c2e-e59c0917e1ca",
    "Metadata": {},
    "ChecksumAlgorithm": 0,
    "ChecksumValidationStatus": 0
  },
  "ContentLength": 814,
  "HttpStatusCode": 200,
  "LoggedAt": "2023-05-24T07:13:05.0413195+00:00"
}
