{
  "AttachmentsContent": [
    {
      "Hash": "6f528ffab34b3f37c2deba99ecd5ab5f3d4b94583f4781ac3f4a95373cc41652",
      "HashType": {
        "Value": "Sha256"
      },
      "Name": "function.zip",
      "Size": 5809425,
      "Url": "https://aws-ssm-document-attachments-us-west-2.s3.us-west-2.amazonaws.com/046/123784938132/Automation/AWS-CreateServiceNowIncident%21ddc7e304-3335-4f93-9c27-720d77581d00/4/function.zip?x-attachment-size=5809425&x-requester-accountId=987868780346&X-Amz-Security-Token=IQoJb3JpZ2luX2VjEI7%2F%2F%2F%2F%2F%2F%2F%2F%2F%2FwEaCXVzLXdlc3QtMiJHMEUCIQDAqnrsxe1MGomcOQcI8YEw40Gn5HXJH8GtM0zO27TyOwIgFHy4KDuVrvuwLimzb%2FZqnCQzm0Ba34o2e8zR%2BqLbk%2BYqwgUI5%2F%2F%2F%2F%2F%2F%2F%2F%2F%2F%2FARADGgwyNDk5MjQ1Mjc0MTAiDJTGgbX6f944dipqgyqWBcgsTqNl7jIPcQPhn%2B1r%2BJCh6flel%2BgsT%2BTMyYlc9hy%2FUJH7oWufnbfsxt1nVAjlUoqaZNwtRYQV%2Br1RqzESbJzFo7UN81H%2F3rBIJctyuyG6%2B2PIB74Jyo%2FlxfkJ4aIwIMw7YObPWNqmnVMxoY6i%2BPttIYS%2BytXm30Ywq0a1rMIHJbrzbJwOzXRrXE%2B4nOPeaYdBuh5NnBS%2BHgym4zwAg9savLJul2tRT4L%2BpBuejou4y5Vq%2BLhILHU4s2FnMf8I1rz4yfTE26b2yS1QZsxBHgfG%2FY%2F86Ttpp7hKupqXtjukKhy0Q3Ke96llQE7Jalr0sB3onrXsmwRXWzDutpwsk9nhy3ucJWyHoj102VGFVXDtA%2Bk1OgYCpZzDTcEAss7cMFIHof%2BfakrtuZXyyvMo%2FT5pWE%2Byv9L33UbrMbUlQ8nTCje4b5%2BmKTvovR3KnqFplbgMyJMo3YkSTL22hbgJPaEPmR2vzHuiEz7mFpFk%2FbvU7yiuPrO5HbkELogCEgNTdgRBsnZpadm46SVZccDS1vCkN0RPRzGawspx76M%2BSG5FpOscZ7RS6cmusIGLfIqlGOJ05nQbZpW0uYVPcCE2kIgHR2FIdDG453LjxhUpfQF4Lvx4dLQBc0Uxd9lBKzVnC9fBtXjAIcN2tWQJR1vV3duFm6%2BELHOD54ydgcnQ1f%2FN4HLHbLeevm8GY2JKou%2BUGcwN7Co8G1ceiVrJAaHMt7zjj5A4rDMyoJC8RXdr9QaGdZQNnViIG3rTfG9B1OSZp9cE6%2FQWSiL2RuTk0Tn3cv1SsxwSeyRFTVQoxD6tgRWzQSWz%2F%2BvkuEXi%2F5vaCyLRXOmvsJfa5AgdoAuHvrc1vUC4L%2F1fSS4z%2B49oZzZ%2FLTBYV%2FtmEWWJMJ7m1KQGOrEBx0pBHzzV5FNokmVjfLFksO9y4UbXHyzwbsveEUR8XPXRtsqi98K0hNdP2dTYICuWuInO9oaHs%2FS74sW3B4qgsXZd1UfKYnSWlxs5O94a0mMMEbK9EOGcc%2Br0Xn%2BaDhvH1yJwHS4qJBho53TAzVwI1GPPjcPmzT5R3V5UeeDnpH13WLXNucQD4DA9NQPUko%2FssBjAMY7vLNhrDR3xc98N3a%2FjpjBUEoWi5p2YP27f64Ln&X-Amz-Algorithm=AWS4-HMAC-SHA256&X-Amz-Date=20230623T071214Z&X-Amz-SignedHeaders=host&X-Amz-Expires=86400&X-Amz-Credential=ASIATUMFJUUZOWP4P5QL%2F20230623%2Fus-west-2%2Fs3%2Faws4_request&X-Amz-Signature=8ee44a4f6d45ae9718287f73e5932cb166542ee78457255b4c6465bbf166c6f5"
    }
  ],
  "Content": "{\n  \"description\" : \"### Document name - AWS-CreateServiceNowIncident\\n\\n## What does this document do?\\nThis document creates an incident in the ServiceNow incident table.\\n\\n## Input Parameters\\n* ServiceNowInstanceUsername: (Required) The name of the user the incident will be created with.\\n* ServiceNowInstancePassword: (Required) The name of an encrypted SSM Parameter containing the password for the ServiceNow user.\\n* ServiceNowInstanceURL: (Required) The url of the ServiceNow instance.\\n* ShortDescription: (Required) A brief description of the incident.\\n* Description: (Required) A detailed explanation on the incident.\\n* [Impact](https://docs.servicenow.com/bundle/helsinki-it-service-management/page/product/incident-management/reference/r_PrioritizationOfIncidents.html): (Optional) The effect an incident has on business:\\n  * Valid Values: High | Medium | Low\\n  * Default: Low\\n* [Urgency](https://docs.servicenow.com/bundle/helsinki-it-service-management/page/product/incident-management/reference/r_PrioritizationOfIncidents.html): (Optional) The extent to which the incident's resolution can bear delay:\\n  * Valid Values: High | Medium | Low\\n  * Default: Low\\n* [Category](https://docs.servicenow.com/bundle/newyork-it-service-management/page/product/incident-management/reference/r_CategorizingIncidents.html): (Optional) The category  of the incident.\\n  * Valid Values: None | Inquiry/Help | Software | Hardware | Network | Database\\n  * Default: None\\n* [Subcategory](https://docs.servicenow.com/bundle/newyork-it-service-management/page/product/incident-management/reference/r_CategorizingIncidents.html): (Optional) The subcategory of the incident.\\n  * Valid Values: None | Antivirus | Email | Internal Application | Operating System | CPU | Disk | Keyboard | Hardware | Memory | Monitor | Mouse | DHCP | DNS | IP Address | VPN | Wireless | DB2 | MS SQL Server | Oracle\\n  * Default: None\\n* AutomationAssumeRole: (Optional) The ARN of the role that allows Automation to perform the actions on your behalf.\\n\\n## Output parameters\\n* Push_incident.incidentID: The created incident ID.\\n\",\n  \"schemaVersion\" : \"0.3\",\n  \"assumeRole\" : \"{{AutomationAssumeRole}}\",\n  \"parameters\" : {\n    \"ServiceNowInstanceUsername\" : {\n      \"type\" : \"String\",\n      \"description\" : \"(Required) The name of the user the incident will be created with.\"\n    },\n    \"ServiceNowInstancePassword\" : {\n      \"type\" : \"String\",\n      \"description\" : \"(Required) The name of an encrypted SSM Parameter containing the password for the ServiceNow user.\"\n    },\n    \"ServiceNowInstanceURL\" : {\n      \"type\" : \"String\",\n      \"description\" : \"(Required) The url of the ServiceNow instance.\"\n    },\n    \"ShortDescription\" : {\n      \"type\" : \"String\",\n      \"description\" : \"(Required) A brief description of the incident.\"\n    },\n    \"Description\" : {\n      \"type\" : \"String\",\n      \"description\" : \"(Required) A detailed explanation on the incident.\"\n    },\n    \"Impact\" : {\n      \"type\" : \"String\",\n      \"default\" : \"Low\",\n      \"description\" : \"(Optional) The effect an incident has on business.\",\n      \"allowedValues\" : [ \"Low\", \"Medium\", \"High\" ]\n    },\n    \"Urgency\" : {\n      \"type\" : \"String\",\n      \"default\" : \"Low\",\n      \"description\" : \"(Optional) The extent to which the incident's resolution can bear delay.\",\n      \"allowedValues\" : [ \"Low\", \"Medium\", \"High\" ]\n    },\n    \"Category\" : {\n      \"type\" : \"String\",\n      \"default\" : \"None\",\n      \"description\" : \"(Optional) The category of the incident.\",\n      \"allowedValues\" : [ \"None\", \"Inquiry / Help\", \"Software\", \"Hardware\", \"Network\", \"Database\" ]\n    },\n    \"Subcategory\" : {\n      \"type\" : \"String\",\n      \"default\" : \"None\",\n      \"description\" : \"(Optional) The subcategory of the incident.\",\n      \"allowedValues\" : [ \"None\", \"Antivirus\", \"Email\", \"Internal Application\", \"Operating System\", \"CPU\", \"Disk\", \"Keyboard\", \"Hardware\", \"Memory\", \"Monitor\", \"Mouse\", \"DHCP\", \"DNS\", \"IP Address\", \"VPN\", \"Wireless\", \"DB2\", \"MS SQL Server\", \"Oracle\" ]\n    },\n    \"AutomationAssumeRole\" : {\n      \"type\" : \"String\",\n      \"description\" : \"(Optional) The ARN of the role that allows Automation to perform the actions on your behalf.\",\n      \"default\" : \"\"\n    }\n  },\n  \"outputs\" : [ \"Push_incident.incidentID\" ],\n  \"mainSteps\" : [ {\n    \"name\" : \"Push_incident\",\n    \"action\" : \"aws:executeScript\",\n    \"outputs\" : [ {\n      \"Name\" : \"incidentID\",\n      \"Selector\" : \"$.Payload.id\",\n      \"Type\" : \"String\"\n    } ],\n    \"inputs\" : {\n      \"Runtime\" : \"python3.8\",\n      \"InputPayload\" : {\n        \"username\" : \"{{ ServiceNowInstanceUsername }}\",\n        \"password\" : \"{{ ServiceNowInstancePassword }}\",\n        \"url\" : \"{{ ServiceNowInstanceURL }}\",\n        \"impact\" : \"{{ Impact }}\",\n        \"urgency\" : \"{{ Urgency }}\",\n        \"short_description\" : \"{{ ShortDescription }}\",\n        \"description\" : \"{{ Description }}\",\n        \"category\" : \"{{ Category }}\",\n        \"subcategory\" : \"{{ Subcategory }}\"\n      },\n      \"Handler\" : \"function.script_handler\",\n      \"Attachment\" : \"function.zip\"\n    }\n  } ],\n  \"files\" : {\n    \"function.zip\" : {\n      \"checksums\" : {\n        \"sha256\" : \"6f528ffab34b3f37c2deba99ecd5ab5f3d4b94583f4781ac3f4a95373cc41652\"\n      },\n      \"size\" : 5809425\n    }\n  }\n}",
  "CreatedDate": "2022-06-21T21:19:10.918Z",
  "DisplayName": null,
  "DocumentFormat": {
    "Value": "JSON"
  },
  "DocumentType": {
    "Value": "Automation"
  },
  "DocumentVersion": "1",
  "Name": "AWS-CreateServiceNowIncident",
  "Requires": [],
  "ReviewStatus": null,
  "Status": {
    "Value": "Active"
  },
  "StatusInformation": null,
  "VersionName": null,
  "ResponseMetadata": {
    "RequestId": "f0d1cc03-fcd3-4c7b-a149-1a5c18ec4434",
    "Metadata": {},
    "ChecksumAlgorithm": 0,
    "ChecksumValidationStatus": 0
  },
  "ContentLength": 8019,
  "HttpStatusCode": 200,
  "LoggedAt": "2023-06-23T07:12:14.4117509+00:00"
}
