{
  "AttachmentsContent": [
    {
      "Hash": "6f528ffab34b3f37c2deba99ecd5ab5f3d4b94583f4781ac3f4a95373cc41652",
      "HashType": {
        "Value": "Sha256"
      },
      "Name": "function.zip",
      "Size": 5809425,
      "Url": "https://aws-ssm-document-attachments-us-west-2.s3.us-west-2.amazonaws.com/dc9/123784938132/Automation/AWS-CreateServiceNowIncident%21ddc7e304-3335-4f93-9c27-720d77581d00/3/function.zip?x-attachment-size=5809425&x-requester-accountId=987868780346&X-Amz-Security-Token=IQoJb3JpZ2luX2VjEIb%2F%2F%2F%2F%2F%2F%2F%2F%2F%2FwEaCXVzLXdlc3QtMiJGMEQCIFCqKlTkSdjdyBMyiopEyad%2BMf2uAk0S7ugGpQmmq%2FtBAiAGv7E6SJvYgXjrqsunemcdbMgstSPBQx%2FtAb%2F03D0qUCqDBAj%2F%2F%2F%2F%2F%2F%2F%2F%2F%2F%2F8BEAMaDDI0OTkyNDUyNzQxMCIMf6IKZnJOvA%2FDI852KtcDFGBNC6TseZgn5jjglcn9%2FLRaIPT%2F3aRBJft%2B87qSocFy406AG5OqcnXqewwwZqHIlwplJgs9l4JKOsky1m1Srht%2BueHiLI3ITxxOZ8qNduMnGWizlj9MhS7H4kKOlDdoNaIlINMgfaPc0M%2BpACHEIn6M2uNhOCdZ2b3sS2CnghI3%2BXK6g1WtnNdq%2FkfGRFzHGdKALyUAdBHNWwrmeMsVVCzwHPPle3MUjuVhjQaJNgaNaDZ6e%2F%2B2Q4q8dvqgdj0tzk%2BrXaoSTC3cVkmaFIGqNFOlbRbyZq0nDInZkbXr7rwgcVjWdfaXxQ0orN%2Fl3E%2FdQ1uCOSRB%2FB8z5M0tp3DZc6m%2BYFM9Q08ZhhqxmX%2Fj6brvoxqipbl46eRVN9Mu5%2FKBx6fW54QeKVbxviTNpy0ZzV%2Bm4Ee%2FzSYG9DMehah8bF16DuH34gU1xkyuNmV1gdtpAg%2BbRZsLGtfIj3CULNld6D2s%2FplQVjltlb99PTVV9t2Qt83Cu%2FiIHHAAxkMd0k%2F7l8%2BMd9ShbC2y9fFrRxGqwA2O5tt7D0aUyjOgWHHKhd15iZZfCi0sZtg31V3Y7pxcPB0h4P92Dl3EUmF%2Br8i%2BlDlaO9u3DCBfG9CjaIauTu4ecw3QpuuKMPSo4JEGOqYBf98zIRLi%2FxFlMKDlgGNd2hQjb3gUhfJN2RCdWf1htOmAxYe%2Fon%2FzJaJoc2234%2BIceefsRXoVl14zt020n7Tv2jBdoWFfqP5Do2Lk0StF%2Bv4R7%2B1%2BWjEKWusxdK9wmtvYR4HLIhI0TNNvlZ2cyZUSChnz%2FDuBLF4IKpLHdp1yQSV1AbHosg6siIML3X9wpdMqo9IrTrYVpy1uzXPmACvU6SwaqLaWSw%3D%3D&X-Amz-Algorithm=AWS4-HMAC-SHA256&X-Amz-Date=20220321T071209Z&X-Amz-SignedHeaders=host&X-Amz-Expires=86400&X-Amz-Credential=ASIATUMFJUUZHWQCOXHF%2F20220321%2Fus-west-2%2Fs3%2Faws4_request&X-Amz-Signature=fe6493753b1d957231bac2faa0b8649216aee2dd6c358c8504632f8276f0e186"
    }
  ],
  "Content": "{\n  \"description\" : \"### Document name - AWS-CreateServiceNowIncident\\n\\n## What does this document do?\\nThis document creates an incident in the ServiceNow incident table.\\n\\n## Input Parameters\\n* ServiceNowInstanceUsername: (Required) The name of the user the incident will be created with.\\n* ServiceNowInstancePassword: (Required) The name of an encrypted SSM Parameter containing the password for the ServiceNow user.\\n* ServiceNowInstanceURL: (Required) The url of the ServiceNow instance.\\n* ShortDescription: (Required) A brief description of the incident.\\n* Description: (Required) A detailed explanation on the incident.\\n* [Impact](https://docs.servicenow.com/bundle/helsinki-it-service-management/page/product/incident-management/reference/r_PrioritizationOfIncidents.html): (Optional) The effect an incident has on business:\\n  * Valid Values: High | Medium | Low\\n  * Default: Low\\n* [Urgency](https://docs.servicenow.com/bundle/helsinki-it-service-management/page/product/incident-management/reference/r_PrioritizationOfIncidents.html): (Optional) The extent to which the incident's resolution can bear delay:\\n  * Valid Values: High | Medium | Low\\n  * Default: Low\\n* [Category](https://docs.servicenow.com/bundle/newyork-it-service-management/page/product/incident-management/reference/r_CategorizingIncidents.html): (Optional) The category  of the incident.\\n  * Valid Values: None | Inquiry/Help | Software | Hardware | Network | Database\\n  * Default: None\\n* [Subcategory](https://docs.servicenow.com/bundle/newyork-it-service-management/page/product/incident-management/reference/r_CategorizingIncidents.html): (Optional) The subcategory of the incident.\\n  * Valid Values: None | Antivirus | Email | Internal Application | Operating System | CPU | Disk | Keyboard | Hardware | Memory | Monitor | Mouse | DHCP | DNS | IP Address | VPN | Wireless | DB2 | MS SQL Server | Oracle\\n  * Default: None\\n* AutomationAssumeRole: (Optional) The ARN of the role that allows Automation to perform the actions on your behalf.\\n\\n## Output parameters\\n* Push_incident.incidentID: The created incident ID.\\n\",\n  \"schemaVersion\" : \"0.3\",\n  \"assumeRole\" : \"{{AutomationAssumeRole}}\",\n  \"parameters\" : {\n    \"ServiceNowInstanceUsername\" : {\n      \"type\" : \"String\",\n      \"description\" : \"(Required) The name of the user the incident will be created with.\"\n    },\n    \"ServiceNowInstancePassword\" : {\n      \"type\" : \"String\",\n      \"description\" : \"(Required) The name of an encrypted SSM Parameter containing the password for the ServiceNow user.\"\n    },\n    \"ServiceNowInstanceURL\" : {\n      \"type\" : \"String\",\n      \"description\" : \"(Required) The url of the ServiceNow instance.\"\n    },\n    \"ShortDescription\" : {\n      \"type\" : \"String\",\n      \"description\" : \"(Required) A brief description of the incident.\"\n    },\n    \"Description\" : {\n      \"type\" : \"String\",\n      \"description\" : \"(Required) A detailed explanation on the incident.\"\n    },\n    \"Impact\" : {\n      \"type\" : \"String\",\n      \"default\" : \"Low\",\n      \"description\" : \"(Optional) The effect an incident has on business.\",\n      \"allowedValues\" : [ \"Low\", \"Medium\", \"High\" ]\n    },\n    \"Urgency\" : {\n      \"type\" : \"String\",\n      \"default\" : \"Low\",\n      \"description\" : \"(Optional) The extent to which the incident's resolution can bear delay.\",\n      \"allowedValues\" : [ \"Low\", \"Medium\", \"High\" ]\n    },\n    \"Category\" : {\n      \"type\" : \"String\",\n      \"default\" : \"None\",\n      \"description\" : \"(Optional) The category of the incident.\",\n      \"allowedValues\" : [ \"None\", \"Inquiry / Help\", \"Software\", \"Hardware\", \"Network\", \"Database\" ]\n    },\n    \"Subcategory\" : {\n      \"type\" : \"String\",\n      \"default\" : \"None\",\n      \"description\" : \"(Optional) The subcategory of the incident.\",\n      \"allowedValues\" : [ \"None\", \"Antivirus\", \"Email\", \"Internal Application\", \"Operating System\", \"CPU\", \"Disk\", \"Keyboard\", \"Hardware\", \"Memory\", \"Monitor\", \"Mouse\", \"DHCP\", \"DNS\", \"IP Address\", \"VPN\", \"Wireless\", \"DB2\", \"MS SQL Server\", \"Oracle\" ]\n    },\n    \"AutomationAssumeRole\" : {\n      \"type\" : \"String\",\n      \"description\" : \"(Optional) The ARN of the role that allows Automation to perform the actions on your behalf.\",\n      \"default\" : \"\"\n    }\n  },\n  \"outputs\" : [ \"Push_incident.incidentID\" ],\n  \"mainSteps\" : [ {\n    \"name\" : \"Push_incident\",\n    \"action\" : \"aws:executeScript\",\n    \"outputs\" : [ {\n      \"Name\" : \"incidentID\",\n      \"Selector\" : \"$.Payload.id\",\n      \"Type\" : \"String\"\n    } ],\n    \"inputs\" : {\n      \"Runtime\" : \"python3.6\",\n      \"InputPayload\" : {\n        \"username\" : \"{{ ServiceNowInstanceUsername }}\",\n        \"password\" : \"{{ ServiceNowInstancePassword }}\",\n        \"url\" : \"{{ ServiceNowInstanceURL }}\",\n        \"impact\" : \"{{ Impact }}\",\n        \"urgency\" : \"{{ Urgency }}\",\n        \"short_description\" : \"{{ ShortDescription }}\",\n        \"description\" : \"{{ Description }}\",\n        \"category\" : \"{{ Category }}\",\n        \"subcategory\" : \"{{ Subcategory }}\"\n      },\n      \"Handler\" : \"function.script_handler\",\n      \"Attachment\" : \"function.zip\"\n    }\n  } ],\n  \"files\" : {\n    \"function.zip\" : {\n      \"checksums\" : {\n        \"sha256\" : \"6f528ffab34b3f37c2deba99ecd5ab5f3d4b94583f4781ac3f4a95373cc41652\"\n      },\n      \"size\" : 5809425\n    }\n  }\n}",
  "CreatedDate": "2020-01-09T00:02:00.265Z",
  "DisplayName": null,
  "DocumentFormat": {
    "Value": "JSON"
  },
  "DocumentType": {
    "Value": "Automation"
  },
  "DocumentVersion": "1",
  "Name": "AWS-CreateServiceNowIncident",
  "Requires": [],
  "ReviewStatus": null,
  "Status": {
    "Value": "Active"
  },
  "StatusInformation": null,
  "VersionName": null,
  "ResponseMetadata": {
    "RequestId": "cc9c41a5-dc3b-4c5d-adfb-68ea5ffd876b",
    "Metadata": {},
    "ChecksumAlgorithm": 0,
    "ChecksumValidationStatus": 0
  },
  "ContentLength": 7745,
  "HttpStatusCode": 200,
  "LoggedAt": "2022-03-21T07:12:09.4717944+00:00"
}
