{
  "AttachmentsContent": [
    {
      "Hash": "6f528ffab34b3f37c2deba99ecd5ab5f3d4b94583f4781ac3f4a95373cc41652",
      "HashType": {
        "Value": "Sha256"
      },
      "Name": "function.zip",
      "Size": 5809425,
      "Url": "https://aws-ssm-document-attachments-us-west-2.s3.us-west-2.amazonaws.com/046/123784938132/Automation/AWS-CreateServiceNowIncident%21ddc7e304-3335-4f93-9c27-720d77581d00/4/function.zip?x-attachment-size=5809425&x-requester-accountId=987868780346&X-Amz-Security-Token=IQoJb3JpZ2luX2VjEP7%2F%2F%2F%2F%2F%2F%2F%2F%2F%2FwEaCXVzLXdlc3QtMiJGMEQCIED8GP9wxw9QOFH9pDmVWi83PvILChEZKoGVC%2FCoeu66AiBpPp7UkEKcZDCSLqaaJWhpM1iflXLaDGktTdH9hBXKjCrVBAiH%2F%2F%2F%2F%2F%2F%2F%2F%2F%2F8BEAMaDDI0OTkyNDUyNzQxMCIM61xUntN5m6ih%2FHGvKqkEkwpMZvOYRMzzLpd8mwcpl5V6I87itNy5L55kPItNapH3CBVAEXap2e3jbFOHtMAT8MWnXdCivBcb8A2JMX79xI6eAr%2FQ%2BBCf6EkPI0tmv85hmwu8EBTRXqN4BM7l0oMntXKJhyTfulMXA0ny0CvVu8lnOU8sqOUQWIzXgfbnRkzkn5WU2mrRunH0uX6hpGwI40oFb0PMQUd3Zgg%2Bl5UlXjqTXeJy4r5mv%2BV0Od4%2B0wO03XaIIDQ6KGP%2F4fN44eJnFGyQ%2FO9%2FpMGAwK5VJQ7PGI6PUu5W1fnAE75L3e6SrUJF8KucRrMsSjaLbEh9RSQlU4ABaHWogLjY9trsMvkiFlY7VdmOiGTXv4H1yYO%2F4RlXF1n1MCByq3fLOU%2F7yvLae4oEFShSZ6IAa3fn4vfwSQTJnmIez6YzwM%2BZtQbBDHalrgQOLIGJULnfJ2ozZA7P4IuQyrnhbuFyzXxyXxWYP%2FoY66027oulYtCw7XPC56RSLovm5W812XHhQiUyYyiW%2FJ6SpQDb2PwRtJU2RXTgEmh%2BitT1iZQWsSMaZPyTHk4Qro88CC6MGjHIby7%2FjO5hM%2F5NwuCEdzm5Rj%2Fs62obktJJW%2FksFlumDB%2FOLs%2FRDfc93ULf3LzWw7dIhgmzQ8aC1%2BJGhYM9QZ4NCe2m4Mow4Shi1woRH8P2iJrMh2AkZ799XctTnTC%2BqJsGxzmcvF%2BM%2B2tiES8Ado97Q7uspvIOK8Isn84loEYdwzDllZKfBjqqAfi6mV6Gt9kQkHyQWFtQ2u%2BDOcpjarFEIfSkUda6RIeUf4A0VAKQUDqAznLn2HTzQ%2BanJ6QzTQvF3r2Xe%2F4e0eECTmZX3P98gi8dR%2FKZeZyAx6v5%2Bemrm4INUy5OSY0yS%2F3thUVt2Jr7bR2mHHtoICSZOaij2l3gZ1%2Fe1CWgXa8b3BM6LhgJF%2BMbjLFsXBu7PbYAK%2BxeXmX3V8vf5xQN%2F1S4vrHW3zJ1ovu3&X-Amz-Algorithm=AWS4-HMAC-SHA256&X-Amz-Date=20230209T071131Z&X-Amz-SignedHeaders=host&X-Amz-Expires=86399&X-Amz-Credential=ASIATUMFJUUZFCM4OBU3%2F20230209%2Fus-west-2%2Fs3%2Faws4_request&X-Amz-Signature=18883f4c327667bac4aaa2ed4b2508499660fe38067434522efd79405a8acb44"
    }
  ],
  "Content": "{\n  \"description\" : \"### Document name - AWS-CreateServiceNowIncident\\n\\n## What does this document do?\\nThis document creates an incident in the ServiceNow incident table.\\n\\n## Input Parameters\\n* ServiceNowInstanceUsername: (Required) The name of the user the incident will be created with.\\n* ServiceNowInstancePassword: (Required) The name of an encrypted SSM Parameter containing the password for the ServiceNow user.\\n* ServiceNowInstanceURL: (Required) The url of the ServiceNow instance.\\n* ShortDescription: (Required) A brief description of the incident.\\n* Description: (Required) A detailed explanation on the incident.\\n* [Impact](https://docs.servicenow.com/bundle/helsinki-it-service-management/page/product/incident-management/reference/r_PrioritizationOfIncidents.html): (Optional) The effect an incident has on business:\\n  * Valid Values: High | Medium | Low\\n  * Default: Low\\n* [Urgency](https://docs.servicenow.com/bundle/helsinki-it-service-management/page/product/incident-management/reference/r_PrioritizationOfIncidents.html): (Optional) The extent to which the incident's resolution can bear delay:\\n  * Valid Values: High | Medium | Low\\n  * Default: Low\\n* [Category](https://docs.servicenow.com/bundle/newyork-it-service-management/page/product/incident-management/reference/r_CategorizingIncidents.html): (Optional) The category  of the incident.\\n  * Valid Values: None | Inquiry/Help | Software | Hardware | Network | Database\\n  * Default: None\\n* [Subcategory](https://docs.servicenow.com/bundle/newyork-it-service-management/page/product/incident-management/reference/r_CategorizingIncidents.html): (Optional) The subcategory of the incident.\\n  * Valid Values: None | Antivirus | Email | Internal Application | Operating System | CPU | Disk | Keyboard | Hardware | Memory | Monitor | Mouse | DHCP | DNS | IP Address | VPN | Wireless | DB2 | MS SQL Server | Oracle\\n  * Default: None\\n* AutomationAssumeRole: (Optional) The ARN of the role that allows Automation to perform the actions on your behalf.\\n\\n## Output parameters\\n* Push_incident.incidentID: The created incident ID.\\n\",\n  \"schemaVersion\" : \"0.3\",\n  \"assumeRole\" : \"{{AutomationAssumeRole}}\",\n  \"parameters\" : {\n    \"ServiceNowInstanceUsername\" : {\n      \"type\" : \"String\",\n      \"description\" : \"(Required) The name of the user the incident will be created with.\"\n    },\n    \"ServiceNowInstancePassword\" : {\n      \"type\" : \"String\",\n      \"description\" : \"(Required) The name of an encrypted SSM Parameter containing the password for the ServiceNow user.\"\n    },\n    \"ServiceNowInstanceURL\" : {\n      \"type\" : \"String\",\n      \"description\" : \"(Required) The url of the ServiceNow instance.\"\n    },\n    \"ShortDescription\" : {\n      \"type\" : \"String\",\n      \"description\" : \"(Required) A brief description of the incident.\"\n    },\n    \"Description\" : {\n      \"type\" : \"String\",\n      \"description\" : \"(Required) A detailed explanation on the incident.\"\n    },\n    \"Impact\" : {\n      \"type\" : \"String\",\n      \"default\" : \"Low\",\n      \"description\" : \"(Optional) The effect an incident has on business.\",\n      \"allowedValues\" : [ \"Low\", \"Medium\", \"High\" ]\n    },\n    \"Urgency\" : {\n      \"type\" : \"String\",\n      \"default\" : \"Low\",\n      \"description\" : \"(Optional) The extent to which the incident's resolution can bear delay.\",\n      \"allowedValues\" : [ \"Low\", \"Medium\", \"High\" ]\n    },\n    \"Category\" : {\n      \"type\" : \"String\",\n      \"default\" : \"None\",\n      \"description\" : \"(Optional) The category of the incident.\",\n      \"allowedValues\" : [ \"None\", \"Inquiry / Help\", \"Software\", \"Hardware\", \"Network\", \"Database\" ]\n    },\n    \"Subcategory\" : {\n      \"type\" : \"String\",\n      \"default\" : \"None\",\n      \"description\" : \"(Optional) The subcategory of the incident.\",\n      \"allowedValues\" : [ \"None\", \"Antivirus\", \"Email\", \"Internal Application\", \"Operating System\", \"CPU\", \"Disk\", \"Keyboard\", \"Hardware\", \"Memory\", \"Monitor\", \"Mouse\", \"DHCP\", \"DNS\", \"IP Address\", \"VPN\", \"Wireless\", \"DB2\", \"MS SQL Server\", \"Oracle\" ]\n    },\n    \"AutomationAssumeRole\" : {\n      \"type\" : \"String\",\n      \"description\" : \"(Optional) The ARN of the role that allows Automation to perform the actions on your behalf.\",\n      \"default\" : \"\"\n    }\n  },\n  \"outputs\" : [ \"Push_incident.incidentID\" ],\n  \"mainSteps\" : [ {\n    \"name\" : \"Push_incident\",\n    \"action\" : \"aws:executeScript\",\n    \"outputs\" : [ {\n      \"Name\" : \"incidentID\",\n      \"Selector\" : \"$.Payload.id\",\n      \"Type\" : \"String\"\n    } ],\n    \"inputs\" : {\n      \"Runtime\" : \"python3.8\",\n      \"InputPayload\" : {\n        \"username\" : \"{{ ServiceNowInstanceUsername }}\",\n        \"password\" : \"{{ ServiceNowInstancePassword }}\",\n        \"url\" : \"{{ ServiceNowInstanceURL }}\",\n        \"impact\" : \"{{ Impact }}\",\n        \"urgency\" : \"{{ Urgency }}\",\n        \"short_description\" : \"{{ ShortDescription }}\",\n        \"description\" : \"{{ Description }}\",\n        \"category\" : \"{{ Category }}\",\n        \"subcategory\" : \"{{ Subcategory }}\"\n      },\n      \"Handler\" : \"function.script_handler\",\n      \"Attachment\" : \"function.zip\"\n    }\n  } ],\n  \"files\" : {\n    \"function.zip\" : {\n      \"checksums\" : {\n        \"sha256\" : \"6f528ffab34b3f37c2deba99ecd5ab5f3d4b94583f4781ac3f4a95373cc41652\"\n      },\n      \"size\" : 5809425\n    }\n  }\n}",
  "CreatedDate": "2022-06-21T21:19:10.918Z",
  "DisplayName": null,
  "DocumentFormat": {
    "Value": "JSON"
  },
  "DocumentType": {
    "Value": "Automation"
  },
  "DocumentVersion": "1",
  "Name": "AWS-CreateServiceNowIncident",
  "Requires": [],
  "ReviewStatus": null,
  "Status": {
    "Value": "Active"
  },
  "StatusInformation": null,
  "VersionName": null,
  "ResponseMetadata": {
    "RequestId": "7ea1395a-be31-4a15-b183-e498cfde6967",
    "Metadata": {},
    "ChecksumAlgorithm": 0,
    "ChecksumValidationStatus": 0
  },
  "ContentLength": 7847,
  "HttpStatusCode": 200,
  "LoggedAt": "2023-02-09T07:11:31.3266438+00:00"
}
