{
  "AttachmentsContent": [],
  "Content": "{\n   \"schemaVersion\": \"2.2\",\n   \"description\": \"This is a sample document\",\n   \"mainSteps\": [\n       {\n         \"action\": \"aws:runShellScript\",\n         \"name\": \"ListFiles\",\n         \"inputs\": {\n            \"commands\": [\"ls\"],\n            \"workingDirectory\": \"/home/ec2-user\",\n            \"executionTimeout\": \"120\"\n         }\n        }\n    ]\n}",
  "CreatedDate": "2023-03-02T07:11:07.262Z",
  "DisplayName": null,
  "DocumentFormat": {
    "Value": "JSON"
  },
  "DocumentType": {
    "Value": "Command"
  },
  "DocumentVersion": "1",
  "Name": "arn:aws:ssm:us-west-2:779076350731:document/AssociationDocumentPublicSharingDocument760537362",
  "Requires": [],
  "ReviewStatus": null,
  "Status": {
    "Value": "Active"
  },
  "StatusInformation": null,
  "VersionName": null,
  "ResponseMetadata": {
    "RequestId": "e9a47ad5-6dd0-4933-9a70-954fb3ffc32f",
    "Metadata": {},
    "ChecksumAlgorithm": 0,
    "ChecksumValidationStatus": 0
  },
  "ContentLength": 626,
  "HttpStatusCode": 200,
  "LoggedAt": "2023-03-02T07:13:08.9459375+00:00"
}
